aelion_calc/__init__.py
aelion_calc/aly.py
aelion_calc/cs_basics.py
aelion_calc/dal.py
aelion_calc/dictionary.py
aelion_calc/gui.py
aelion_calc/hack.py
aelion_calc/health.py
aelion_calc/manual.py
aelion_calc/math_tools.py
aelion_calc/say.py
aelion_calc/storage.py
aelion_calc/test.py
aelion_calc-1.4.0.dist-info/METADATA
aelion_calc-1.4.0.dist-info/WHEEL
aelion_calc-1.4.0.dist-info/top_level.txt
aelion_calc-1.4.0.dist-info/RECORD
