Metadata-Version: 2.4
Name: aelion_calc
Version: 1.4.0
Summary: A powerful student library: Data Science, GenAI, Ethical Hacking, and the ZenithOS GUI Framework (Build & Compile Desktop Apps).
Author-email: Rana Ahmad <elearninfo786@gmail.com>
Project-URL: Homepage, https://github.com/yourusername/aelion_calc
Classifier: Programming Language :: Python :: 3
Classifier: License :: OSI Approved :: MIT License
Classifier: Operating System :: OS Independent
Classifier: Intended Audience :: Education
Classifier: Intended Audience :: Developers
Classifier: Intended Audience :: Science/Research
Classifier: Topic :: Scientific/Engineering :: Artificial Intelligence
Classifier: Topic :: Scientific/Engineering :: Information Analysis
Classifier: Topic :: Security
Classifier: Topic :: Security :: Cryptography
Classifier: Topic :: Software Development :: User Interfaces
Classifier: Topic :: Software Development :: Libraries :: Python Modules
Classifier: Topic :: Desktop Environment
Requires-Python: >=3.7
Provides-Extra: gui
Requires-Dist: plyer; extra == "gui"
Requires-Dist: cryptography; extra == "gui"
Requires-Dist: opencv-python; extra == "gui"
Requires-Dist: pyinstaller; extra == "gui"
